bandcamp_search/__init__.py
bandcamp_search/__main__.py
bandcamp_search/models.py
bandcamp_search/search.py
bandcamp_search-0.1.0.dist-info/LICENSE
bandcamp_search-0.1.0.dist-info/METADATA
bandcamp_search-0.1.0.dist-info/WHEEL
bandcamp_search-0.1.0.dist-info/RECORD
