Metadata-Version: 2.1
Name: bandcamp-search
Version: 0.1.0
Summary: Search for items on bandcamp
License: MIT
Author: iamthefij
Requires-Python: >=3.11,<4.0
Classifier: License :: OSI Approved :: MIT License
Classifier: Programming Language :: Python :: 3
Classifier: Programming Language :: Python :: 3.11
Classifier: Programming Language :: Python :: 3.12
Classifier: Programming Language :: Python :: 3.13
Requires-Dist: requests (>=2.32.3,<3.0.0)
